odoo8_addon_purchase_origin_address-8.0.1.0.0-py2.7-nspkg.pth
odoo8_addon_purchase_origin_address-8.0.1.0.0.dist-info/top_level.txt
odoo8_addon_purchase_origin_address-8.0.1.0.0.dist-info/WHEEL
odoo8_addon_purchase_origin_address-8.0.1.0.0.dist-info/RECORD
odoo8_addon_purchase_origin_address-8.0.1.0.0.dist-info/metadata.json
odoo8_addon_purchase_origin_address-8.0.1.0.0.dist-info/DESCRIPTION.rst
odoo8_addon_purchase_origin_address-8.0.1.0.0.dist-info/METADATA
odoo8_addon_purchase_origin_address-8.0.1.0.0.dist-info/namespace_packages.txt
odoo_addons/purchase_origin_address/__openerp__.py
odoo_addons/purchase_origin_address/__init__.py
odoo_addons/purchase_origin_address/README.rst
odoo_addons/purchase_origin_address/i18n/purchase_origin_address.pot
odoo_addons/purchase_origin_address/static/description/icon.png
